neowGen.py
neowGenerator.py
neowGen-0.0.4.dist-info/LICENSE
neowGen-0.0.4.dist-info/METADATA
neowGen-0.0.4.dist-info/WHEEL
neowGen-0.0.4.dist-info/top_level.txt
neowGen-0.0.4.dist-info/RECORD
