Metadata-Version: 2.1
Name: neowGen
Version: 0.0.4
Summary: A HuggingFace LLM dataset pipeline generator
Home-page: https://github.com/pechaut78/neowGen
Author: Pierre-Emmanuel CHAUT
Author-email: pe_chaut@hotmail.com
Classifier: Programming Language :: Python :: 3
Classifier: Programming Language :: Python :: 3.6
Classifier: Programming Language :: Python :: 3.7
Classifier: Programming Language :: Python :: 3.8
Classifier: Programming Language :: Python :: 3.9
Classifier: Programming Language :: Python :: 3.10
Classifier: License :: OSI Approved :: MIT License
Classifier: Operating System :: OS Independent
License-File: LICENSE
Requires-Dist: pandas
Requires-Dist: tqdm
Requires-Dist: numpy
Requires-Dist: huggingface-hub
Requires-Dist: datasets
